{
	"info": {
		"_postman_id": "91139dc9-f2a5-476a-beba-22dcc056f152",
		"name": "transport-app",
		"schema": "https://schema.getpostman.com/json/collection/v2.1.0/collection.json",
		"_exporter_id": "22650281"
	},
	"item": [
		{
			"name": "HEALTH",
			"request": {
				"auth": {
					"type": "noauth"
				},
				"method": "GET",
				"header": [],
				"url": {
					"raw": "https://einar-main-f0820bc.d2.zuplo.dev/health",
					"protocol": "https",
					"host": [
						"einar-main-f0820bc",
						"d2",
						"zuplo",
						"dev"
					],
					"path": [
						"health"
					]
				}
			},
			"response": []
		},
		{
			"name": "REGISTER",
			"request": {
				"method": "POST",
				"header": [],
				"body": {
					"mode": "raw",
					"raw": "{\r\n    \"email\": \"test123456@gmail.com\",\r\n    \"password\": \"Password.,2019\"\r\n}",
					"options": {
						"raw": {
							"language": "json"
						}
					}
				},
				"url": {
					"raw": "{{TRANSPORT_APP_HOST}}/register",
					"host": [
						"{{TRANSPORT_APP_HOST}}"
					],
					"path": [
						"register"
					]
				}
			},
			"response": []
		},
		{
			"name": "LOGIN",
			"request": {
				"method": "POST",
				"header": [],
				"body": {
					"mode": "raw",
					"raw": "{\r\n    \"email\": \"ignaciovl2.j@gmail.com\",\r\n    \"password\": \"Password.,2019\"\r\n}",
					"options": {
						"raw": {
							"language": "json"
						}
					}
				},
				"url": {
					"raw": "{{TRANSPORT_APP_HOST}}/login",
					"host": [
						"{{TRANSPORT_APP_HOST}}"
					],
					"path": [
						"login"
					]
				}
			},
			"response": []
		},
		{
			"name": "CREATE ORGANIZATION",
			"request": {
				"auth": {
					"type": "noauth"
				},
				"method": "POST",
				"header": [
					{
						"key": "country",
						"value": "CL",
						"type": "text"
					}
				],
				"body": {
					"mode": "raw",
					"raw": "{\r\n    \"name\": \"MY EINAR ORGANIZATION\",\r\n    \"email\": \"ignaciovl2.j@gmail.com\"\r\n}",
					"options": {
						"raw": {
							"language": "json"
						}
					}
				},
				"url": {
					"raw": "{{TRANSPORT_APP_HOST}}/organizations",
					"host": [
						"{{TRANSPORT_APP_HOST}}"
					],
					"path": [
						"organizations"
					]
				}
			},
			"response": []
		},
		{
			"name": "UPSERT PLAN",
			"request": {
				"auth": {
					"type": "bearer",
					"bearer": [
						{
							"key": "token",
							"value": "{{FIREBASE_ID_TOKEN}}",
							"type": "string"
						}
					]
				},
				"method": "POST",
				"header": [
					{
						"key": "organization",
						"value": "1-CL",
						"type": "text"
					}
				],
				"body": {
					"mode": "raw",
					"raw": "{\r\n    \"referenceID\": \"operator-reference-plannedDate\",\r\n    \"plannedDate\": \"2025-01-03\",\r\n    \"timeWindow\": {\r\n        \"startTime\": \"09:00\",\r\n        \"endTime\": \"18:00\"\r\n    },\r\n    \"startLocation\": {\r\n        \"nodeReferenceID\": \"\",\r\n        \"latitude\": -0.127627,\r\n        \"longitude\": 51.503355\r\n    },\r\n    \"unassignedOrders\": null,\r\n    \"routes\": [\r\n        {\r\n            \"referenceID\": \"operator-reference-plannedDate\",\r\n            \"container\": {\r\n                \"lpn\": \"12345678\"\r\n            },\r\n            \"operator\": {\r\n                \"referenceID\": \"operatorReference\"\r\n            },\r\n            \"endLocation\": {\r\n                \"nodeReferenceID\": \"12345\",\r\n                \"latitude\": -0.127627,\r\n                \"longitude\": 51.503355\r\n            },\r\n            \"visits\": [\r\n                {\r\n                    \"sequence\": 1,\r\n                    \"latitude\": 51.507884,\r\n                    \"longitude\": -0.074146,\r\n                    \"orders\": [\r\n                        {\r\n                            \"referenceID\": \"reference_3\",\r\n                            \"collectAvailabilityDate\": {\r\n                                \"date\": \"0001-01-01\",\r\n                                \"timeRange\": {\r\n                                    \"endTime\": \"\",\r\n                                    \"startTime\": \"\"\r\n                                }\r\n                            },\r\n                            \"destination\": {\r\n                                \"addressInfo\": {\r\n                                    \"addressLine1\": \"Inglaterra 59\",\r\n                                    \"addressLine2\": \"La Florida\",\r\n                                    \"addressLine3\": \"Santiago, Chile\",\r\n                                    \"contact\": {\r\n                                        \"email\": \"\",\r\n                                        \"phone\": \"\",\r\n                                        \"nationalID\": \"\",\r\n                                        \"documents\": null,\r\n                                        \"fullName\": \"\"\r\n                                    },\r\n                                    \"district\": \"Santiago\",\r\n                                    \"latitude\": 51.508037,\r\n                                    \"longitude\": -0.076134,\r\n                                    \"province\": \"Santiago\",\r\n                                    \"state\": \"RM\",\r\n                                    \"timeZone\": \"America/Santiago\",\r\n                                    \"zipCode\": \"8320000\"\r\n                                },\r\n                                \"deliveryInstructions\": \"Departamento nº 2214\",\r\n                                \"nodeInfo\": {\r\n                                    \"referenceId\": \"destination-node-3\",\r\n                                    \"name\": \"\"\r\n                                }\r\n                            },\r\n                            \"items\": [],\r\n                            \"orderType\": {\r\n                                \"description\": \"\",\r\n                                \"type\": \"\"\r\n                            },\r\n                            \"origin\": {\r\n                                \"addressInfo\": {\r\n                                    \"addressLine1\": \"\",\r\n                                    \"addressLine2\": \"\",\r\n                                    \"addressLine3\": \"\",\r\n                                    \"contact\": {\r\n                                        \"email\": \"\",\r\n                                        \"phone\": \"\",\r\n                                        \"nationalID\": \"\",\r\n                                        \"documents\": null,\r\n                                        \"fullName\": \"\"\r\n                                    },\r\n                                    \"district\": \"\",\r\n                                    \"latitude\": 0,\r\n                                    \"longitude\": 0,\r\n                                    \"province\": \"\",\r\n                                    \"state\": \"\",\r\n                                    \"timeZone\": \"\",\r\n                                    \"zipCode\": \"\"\r\n                                },\r\n                                \"nodeInfo\": {\r\n                                    \"referenceId\": \"\",\r\n                                    \"name\": \"\"\r\n                                }\r\n                            },\r\n                            \"packages\": [],\r\n                            \"promisedDate\": {\r\n                                \"dateRange\": {\r\n                                    \"endDate\": \"0001-01-01\",\r\n                                    \"startDate\": \"0001-01-01\"\r\n                                },\r\n                                \"serviceCategory\": \"\",\r\n                                \"timeRange\": {\r\n                                    \"endTime\": \"\",\r\n                                    \"startTime\": \"\"\r\n                                }\r\n                            },\r\n                            \"references\": [],\r\n                            \"transportRequirements\": [],\r\n                            \"businessIdentifiers\": {\r\n                                \"commerce\": \"\",\r\n                                \"consumer\": \"\"\r\n                            },\r\n                            \"orderStatus\": {\r\n                                \"ID\": 0,\r\n                                \"status\": \"\",\r\n                                \"createdAt\": \"0001-01-01T00:00:00Z\"\r\n                            }\r\n                        }\r\n                    ]\r\n                },\r\n                {\r\n                    \"sequence\": 2,\r\n                    \"latitude\": 51.509562,\r\n                    \"longitude\": -0.0872,\r\n                    \"orders\": [\r\n                        {\r\n                            \"referenceID\": \"reference_2\",\r\n                            \"collectAvailabilityDate\": {\r\n                                \"date\": \"0001-01-01\",\r\n                                \"timeRange\": {\r\n                                    \"endTime\": \"\",\r\n                                    \"startTime\": \"\"\r\n                                }\r\n                            },\r\n                            \"destination\": {\r\n                                \"addressInfo\": {\r\n                                    \"addressLine1\": \"Inglaterra 59\",\r\n                                    \"addressLine2\": \"La Florida\",\r\n                                    \"addressLine3\": \"Santiago, Chile\",\r\n                                    \"contact\": {\r\n                                        \"email\": \"\",\r\n                                        \"phone\": \"\",\r\n                                        \"nationalID\": \"\",\r\n                                        \"documents\": null,\r\n                                        \"fullName\": \"\"\r\n                                    },\r\n                                    \"district\": \"Santiago\",\r\n                                    \"latitude\": 51.509562,\r\n                                    \"longitude\": -0.087199,\r\n                                    \"province\": \"Santiago\",\r\n                                    \"state\": \"RM\",\r\n                                    \"timeZone\": \"America/Santiago\",\r\n                                    \"zipCode\": \"8320000\"\r\n                                },\r\n                                \"deliveryInstructions\": \"Departamento nº 2214\",\r\n                                \"nodeInfo\": {\r\n                                    \"referenceId\": \"destination-node-2\",\r\n                                    \"name\": \"\"\r\n                                }\r\n                            },\r\n                            \"items\": [],\r\n                            \"orderType\": {\r\n                                \"description\": \"\",\r\n                                \"type\": \"\"\r\n                            },\r\n                            \"origin\": {\r\n                                \"addressInfo\": {\r\n                                    \"addressLine1\": \"\",\r\n                                    \"addressLine2\": \"\",\r\n                                    \"addressLine3\": \"\",\r\n                                    \"contact\": {\r\n                                        \"email\": \"\",\r\n                                        \"phone\": \"\",\r\n                                        \"nationalID\": \"\",\r\n                                        \"documents\": null,\r\n                                        \"fullName\": \"\"\r\n                                    },\r\n                                    \"district\": \"\",\r\n                                    \"latitude\": 0,\r\n                                    \"longitude\": 0,\r\n                                    \"province\": \"\",\r\n                                    \"state\": \"\",\r\n                                    \"timeZone\": \"\",\r\n                                    \"zipCode\": \"\"\r\n                                },\r\n                                \"nodeInfo\": {\r\n                                    \"referenceId\": \"\",\r\n                                    \"name\": \"\"\r\n                                }\r\n                            },\r\n                            \"packages\": [],\r\n                            \"promisedDate\": {\r\n                                \"dateRange\": {\r\n                                    \"endDate\": \"0001-01-01\",\r\n                                    \"startDate\": \"0001-01-01\"\r\n                                },\r\n                                \"serviceCategory\": \"\",\r\n                                \"timeRange\": {\r\n                                    \"endTime\": \"\",\r\n                                    \"startTime\": \"\"\r\n                                }\r\n                            },\r\n                            \"references\": [],\r\n                            \"transportRequirements\": [],\r\n                            \"businessIdentifiers\": {\r\n                                \"commerce\": \"\",\r\n                                \"consumer\": \"\"\r\n                            },\r\n                            \"orderStatus\": {\r\n                                \"ID\": 0,\r\n                                \"status\": \"\",\r\n                                \"createdAt\": \"0001-01-01T00:00:00Z\"\r\n                            }\r\n                        }\r\n                    ]\r\n                },\r\n                {\r\n                    \"sequence\": 3,\r\n                    \"latitude\": 51.503174,\r\n                    \"longitude\": -0.126406,\r\n                    \"orders\": [\r\n                        {\r\n                            \"referenceID\": \"reference_1\",\r\n                            \"collectAvailabilityDate\": {\r\n                                \"date\": \"0001-01-01\",\r\n                                \"timeRange\": {\r\n                                    \"endTime\": \"\",\r\n                                    \"startTime\": \"\"\r\n                                }\r\n                            },\r\n                            \"destination\": {\r\n                                \"addressInfo\": {\r\n                                    \"addressLine1\": \"Inglaterra 59\",\r\n                                    \"addressLine2\": \"La Florida\",\r\n                                    \"addressLine3\": \"Santiago, Chile\",\r\n                                    \"contact\": {\r\n                                        \"email\": \"\",\r\n                                        \"phone\": \"\",\r\n                                        \"nationalID\": \"\",\r\n                                        \"documents\": null,\r\n                                        \"fullName\": \"\"\r\n                                    },\r\n                                    \"district\": \"Santiago\",\r\n                                    \"latitude\": 51.503355,\r\n                                    \"longitude\": -0.127627,\r\n                                    \"province\": \"Santiago\",\r\n                                    \"state\": \"RM\",\r\n                                    \"timeZone\": \"America/Santiago\",\r\n                                    \"zipCode\": \"8320000\"\r\n                                },\r\n                                \"deliveryInstructions\": \"Departamento nº 2214\",\r\n                                \"nodeInfo\": {\r\n                                    \"referenceId\": \"destination-node-1\",\r\n                                    \"name\": \"\"\r\n                                }\r\n                            },\r\n                            \"items\": [],\r\n                            \"orderType\": {\r\n                                \"description\": \"\",\r\n                                \"type\": \"\"\r\n                            },\r\n                            \"origin\": {\r\n                                \"addressInfo\": {\r\n                                    \"addressLine1\": \"\",\r\n                                    \"addressLine2\": \"\",\r\n                                    \"addressLine3\": \"\",\r\n                                    \"contact\": {\r\n                                        \"email\": \"\",\r\n                                        \"phone\": \"\",\r\n                                        \"nationalID\": \"\",\r\n                                        \"documents\": null,\r\n                                        \"fullName\": \"\"\r\n                                    },\r\n                                    \"district\": \"\",\r\n                                    \"latitude\": 0,\r\n                                    \"longitude\": 0,\r\n                                    \"province\": \"\",\r\n                                    \"state\": \"\",\r\n                                    \"timeZone\": \"\",\r\n                                    \"zipCode\": \"\"\r\n                                },\r\n                                \"nodeInfo\": {\r\n                                    \"referenceId\": \"\",\r\n                                    \"name\": \"\"\r\n                                }\r\n                            },\r\n                            \"packages\": [],\r\n                            \"promisedDate\": {\r\n                                \"dateRange\": {\r\n                                    \"endDate\": \"0001-01-01\",\r\n                                    \"startDate\": \"0001-01-01\"\r\n                                },\r\n                                \"serviceCategory\": \"\",\r\n                                \"timeRange\": {\r\n                                    \"endTime\": \"\",\r\n                                    \"startTime\": \"\"\r\n                                }\r\n                            },\r\n                            \"references\": [],\r\n                            \"transportRequirements\": [],\r\n                            \"businessIdentifiers\": {\r\n                                \"commerce\": \"\",\r\n                                \"consumer\": \"\"\r\n                            },\r\n                            \"orderStatus\": {\r\n                                \"ID\": 0,\r\n                                \"status\": \"\",\r\n                                \"createdAt\": \"0001-01-01T00:00:00Z\"\r\n                            }\r\n                        }\r\n                    ]\r\n                }\r\n            ]\r\n        }\r\n    ]\r\n}",
					"options": {
						"raw": {
							"language": "json"
						}
					}
				},
				"url": {
					"raw": "{{TRANSPORT_APP_HOST}}/plans",
					"host": [
						"{{TRANSPORT_APP_HOST}}"
					],
					"path": [
						"plans"
					]
				}
			},
			"response": [
				{
					"name": "UPSERT DAILY PLAN",
					"originalRequest": {
						"method": "POST",
						"header": [
							{
								"key": "X-Access-Token",
								"value": "{{ACCESS_TOKEN}}",
								"type": "text"
							},
							{
								"key": "organization-key",
								"value": "{{ORGANIZATION_KEY}}",
								"type": "text"
							},
							{
								"key": "country",
								"value": "CL",
								"type": "text"
							}
						],
						"body": {
							"mode": "raw",
							"raw": "{\r\n    \"referenceID\": \"operator-reference-plannedDate\",\r\n    \"plannedDate\": \"2025-01-03\",\r\n    \"startLocation\": {\r\n        \"nodeReferenceID\": \"12345\",\r\n        \"latitude\": -0.127627,\r\n        \"longitude\": 51.503355\r\n    },\r\n    \"unassignedOrders\": [\r\n        {\r\n            \"longitude\": -0.127627,\r\n            \"latitude\": 51.503355,\r\n            \"referenceID\": \"reference_1\"\r\n        },\r\n        {\r\n            \"longitude\": -0.087199,\r\n            \"latitude\": 51.509562,\r\n            \"referenceID\": \"reference_2\"\r\n        },\r\n        {\r\n            \"longitude\": -0.076134,\r\n            \"latitude\": 51.508037,\r\n            \"referenceID\": \"reference_3\"\r\n        }\r\n    ],\r\n    \"routes\": [\r\n        {\r\n            \"referenceID\": \"operator-reference-plannedDate\",\r\n            \"operator\": {\r\n                \"referenceID\": \"operatorReference\"\r\n            },\r\n            \"endLocation\": {\r\n                \"nodeReferenceID\": \"12345\",\r\n                \"latitude\": -0.127627,\r\n                \"longitude\": 51.503355\r\n            }\r\n        }\r\n    ]\r\n}",
							"options": {
								"raw": {
									"language": "json"
								}
							}
						},
						"url": {
							"raw": "{{TRANSPORT_APP_HOST}}/plans",
							"host": [
								"{{TRANSPORT_APP_HOST}}"
							],
							"path": [
								"plans"
							]
						}
					},
					"_postman_previewlanguage": "Text",
					"header": [],
					"cookie": [],
					"body": ""
				},
				{
					"name": "UPSERT OPTIMIZED DAILY PLAN",
					"originalRequest": {
						"method": "POST",
						"header": [
							{
								"key": "X-Access-Token",
								"value": "{{ACCESS_TOKEN}}",
								"type": "text"
							},
							{
								"key": "organization-key",
								"value": "{{ORGANIZATION_KEY}}",
								"type": "text"
							},
							{
								"key": "country",
								"value": "CL",
								"type": "text"
							}
						],
						"body": {
							"mode": "raw",
							"raw": "{\r\n    \"referenceID\": \"reference_8-2025-01-03\",\r\n    \"plannedDate\": \"2025-01-03\",\r\n    \"routes\": [\r\n        {\r\n            \"referenceID\": \"reference_8-2025-01-03\",\r\n            \"operator\": {\r\n                \"referenceID\": \"reference_8\"\r\n            },\r\n            \"visits\": [\r\n                {\r\n                    \"latitude\": 1.0,\r\n                    \"longitude\": 1.0,\r\n                    \"sequence\": 1,\r\n                    \"orders\": [\r\n                        {\r\n                            \"referenceID\": \"reference_1\"\r\n                        }\r\n                    ]\r\n                }\r\n            ]\r\n        }\r\n    ]\r\n}",
							"options": {
								"raw": {
									"language": "json"
								}
							}
						},
						"url": {
							"raw": "{{TRANSPORT_APP_HOST}}/plans",
							"host": [
								"{{TRANSPORT_APP_HOST}}"
							],
							"path": [
								"plans"
							]
						}
					},
					"_postman_previewlanguage": "Text",
					"header": [],
					"cookie": [],
					"body": ""
				}
			]
		},
		{
			"name": "SEARCH PLAN BY REFERENCE",
			"protocolProfileBehavior": {
				"disableBodyPruning": true
			},
			"request": {
				"auth": {
					"type": "bearer",
					"bearer": [
						{
							"key": "token",
							"value": "{{FIREBASE_ID_TOKEN}}",
							"type": "string"
						}
					]
				},
				"method": "GET",
				"header": [
					{
						"key": "organization",
						"value": "150001-CL",
						"type": "text"
					}
				],
				"body": {
					"mode": "raw",
					"raw": "",
					"options": {
						"raw": {
							"language": "json"
						}
					}
				},
				"url": {
					"raw": "{{TRANSPORT_APP_HOST}}/plans/{{referenceID}}",
					"host": [
						"{{TRANSPORT_APP_HOST}}"
					],
					"path": [
						"plans",
						"{{referenceID}}"
					]
				}
			},
			"response": [
				{
					"name": "SEARCH PLAN BY REFERENCE",
					"originalRequest": {
						"method": "GET",
						"header": [],
						"url": {
							"raw": "{{TRANSPORT_APP_HOST}}/plans/{{referenceID}}",
							"host": [
								"{{TRANSPORT_APP_HOST}}"
							],
							"path": [
								"plans",
								"{{referenceID}}"
							]
						}
					},
					"_postman_previewlanguage": "json",
					"header": [
						{
							"key": "Content-Type",
							"value": "application/json",
							"description": "",
							"type": "text"
						}
					],
					"cookie": [],
					"body": "{\n    \"referenceID\": \"reference_8-2025-01-03\",\n    \"plannedDate\": \"2025-01-03\",\n    \"startLocation\": {\n        \"nodeReferenceID\": \"12345\",\n        \"latitude\": -0.127627,\n        \"longitude\": 51.503355\n    },\n    \"unassignedOrders\": [\n        {\n            \"longitude\": -0.076134,\n            \"latitude\": 51.508037,\n            \"referenceID\": \"reference_3\"\n        },\n        {\n            \"longitude\": -0.087199,\n            \"latitude\": 51.509562,\n            \"referenceID\": \"reference_2\"\n        },\n        {\n            \"longitude\": -0.127627,\n            \"latitude\": 51.503355,\n            \"referenceID\": \"reference_1\"\n        }\n    ],\n    \"routes\": [\n        {\n            \"referenceID\": \"reference_8-2025-01-03\",\n            \"operator\": {\n                \"referenceID\": \"reference_8\"\n            },\n            \"endLocation\": {\n                \"nodeReferenceID\": \"12345\",\n                \"latitude\": -0.127627,\n                \"longitude\": 51.503355\n            },\n            \"visits\": [\n                {\n                    \"referenceID\": \"1234\",\n                    \"sequence\": 1,\n                    \"latitude\": 1.0,\n                    \"longitude\": 1.0,\n                    \"orders\": [\n                        [\n                            {\n                                \"referenceID\": \"reference_1\",\n                                \"businessIdentifiers\": {\n                                    \"commerce\": \"COMMERCE_EXAMPLE2AAA\",\n                                    \"consumer\": \"CONSUMER_EXAMPLE\"\n                                },\n                                \"orderStatus\": {\n                                    \"ID\": 0,\n                                    \"status\": \"planned\",\n                                    \"createdAt\": \"0001-01-01T00:00:00Z\"\n                                },\n                                \"collectAvailabilityDate\": {\n                                    \"date\": \"2022-03-09\",\n                                    \"timeRange\": {\n                                        \"endTime\": \"03:41\",\n                                        \"startTime\": \"03:41\"\n                                    }\n                                },\n                                \"destination\": {\n                                    \"addressInfo\": {\n                                        \"addressLine1\": \"string24\",\n                                        \"addressLine2\": \"string24\",\n                                        \"addressLine3\": \"string24\",\n                                        \"contact\": {\n                                            \"email\": \"string24161\",\n                                            \"phone\": \"string242\",\n                                            \"nationalID\": \"string24\",\n                                            \"documents\": [\n                                                {\n                                                    \"type\": \"string24\",\n                                                    \"value\": \"string24\"\n                                                }\n                                            ],\n                                            \"fullName\": \"string24name\"\n                                        },\n                                        \"county\": \"string24\",\n                                        \"district\": \"string24\",\n                                        \"latitude\": 100.0,\n                                        \"longitude\": 100.0,\n                                        \"province\": \"string24\",\n                                        \"state\": \"string24\",\n                                        \"timeZone\": \"string24\",\n                                        \"zipCode\": \"string24\"\n                                    },\n                                    \"deliveryInstructions\": \"entregar en mi house\",\n                                    \"nodeInfo\": {\n                                        \"referenceId\": \"string244XD\"\n                                    }\n                                },\n                                \"items\": [\n                                    {\n                                        \"description\": \"string24\",\n                                        \"dimensions\": {\n                                            \"Length\": 1.0,\n                                            \"height\": 1.0,\n                                            \"unit\": \"string24\",\n                                            \"width\": 1.0\n                                        },\n                                        \"insurance\": {\n                                            \"currency\": \"CLP\",\n                                            \"unitValue\": 1.0\n                                        },\n                                        \"logisticCondition\": \"string24\",\n                                        \"quantity\": {\n                                            \"quantityNumber\": 1,\n                                            \"quantityUnit\": \"C/U\"\n                                        },\n                                        \"referenceId\": \"string24\",\n                                        \"weight\": {\n                                            \"unit\": \"string24\",\n                                            \"value\": 1.0\n                                        }\n                                    }\n                                ],\n                                \"orderType\": {\n                                    \"description\": \"JOJOJO\",\n                                    \"type\": \"string24\"\n                                },\n                                \"origin\": {\n                                    \"addressInfo\": {\n                                        \"addressLine1\": \"string24\",\n                                        \"addressLine2\": \"string24\",\n                                        \"addressLine3\": \"string24\",\n                                        \"contact\": {\n                                            \"email\": \"string24\",\n                                            \"phone\": \"string24\",\n                                            \"nationalID\": \"string24\",\n                                            \"documents\": [\n                                                {\n                                                    \"type\": \"string24\",\n                                                    \"value\": \"string24\"\n                                                }\n                                            ],\n                                            \"fullName\": \"string24\"\n                                        },\n                                        \"county\": \"string24\",\n                                        \"district\": \"string24\",\n                                        \"latitude\": 1.0,\n                                        \"longitude\": 1.0,\n                                        \"province\": \"string24\",\n                                        \"state\": \"string24\",\n                                        \"timeZone\": \"string24\",\n                                        \"zipCode\": \"string24\"\n                                    },\n                                    \"nodeInfo\": {\n                                        \"referenceId\": \"string24\"\n                                    }\n                                },\n                                \"packages\": [\n                                    {\n                                        \"dimensions\": {\n                                            \"Length\": 1.0,\n                                            \"height\": 1.0,\n                                            \"unit\": \"string24\",\n                                            \"width\": 1.0\n                                        },\n                                        \"insurance\": {\n                                            \"currency\": \"string242\",\n                                            \"unitValue\": 1.0\n                                        },\n                                        \"itemReferences\": [\n                                            {\n                                                \"quantity\": {\n                                                    \"quantityNumber\": 1,\n                                                    \"quantityUnit\": \"string24\"\n                                                },\n                                                \"referenceId\": \"string24\"\n                                            }\n                                        ],\n                                        \"lpn\": \"string24\",\n                                        \"packageType\": \"default\",\n                                        \"weight\": {\n                                            \"unit\": \"string24\",\n                                            \"value\": 1.0\n                                        }\n                                    }\n                                ],\n                                \"promisedDate\": {\n                                    \"dateRange\": {\n                                        \"endDate\": \"2025-03-09\",\n                                        \"startDate\": \"2025-03-09\"\n                                    },\n                                    \"serviceCategory\": \"\",\n                                    \"timeRange\": {\n                                        \"endTime\": \"03:30\",\n                                        \"startTime\": \"03:30\"\n                                    }\n                                },\n                                \"references\": [\n                                    {\n                                        \"type\": \"string24\",\n                                        \"value\": \"string24\"\n                                    }\n                                ],\n                                \"transportRequirements\": [\n                                    {\n                                        \"type\": \"string24\",\n                                        \"value\": \"string24\"\n                                    }\n                                ]\n                            }\n                        ]\n                    ]\n                }\n            ]\n        }\n    ]\n}"
				}
			]
		},
		{
			"name": "PLAN OPTIMIZATION",
			"request": {
				"auth": {
					"type": "noauth"
				},
				"method": "POST",
				"header": [],
				"body": {
					"mode": "raw",
					"raw": "{\r\n    \"referenceID\": \"operator-reference-plannedDate\",\r\n    \"plannedDate\": \"2025-01-03\",\r\n    \"startLocation\": {\r\n        \"latitude\": -0.127627,\r\n        \"longitude\": 51.503355\r\n    },\r\n    \"unassignedOrders\": [\r\n        {\r\n            \"longitude\": -0.076134,\r\n            \"latitude\": 51.508037,\r\n            \"address\": \"Inglaterra 59, La florida, Santiago, Chile\",\r\n            \"notes\": \"Departamento nº 2214\",\r\n            \"receiverName\": \"Ignacio Jeria\",\r\n            \"receiverPhone\": \"+56957857558\",\r\n            \"referenceID\": \"reference_3\"\r\n        },\r\n        {\r\n            \"longitude\": -0.087199,\r\n            \"latitude\": 51.509562,\r\n            \"address\": \"Inglaterra 59, La florida, Santiago Chile\",\r\n            \"notes\": \"Departamento nº 2214\",\r\n            \"receiverName\": \"Ignacio Jeria\",\r\n            \"receiverPhone\": \"+56957857558\",\r\n            \"referenceID\": \"reference_2\"\r\n        },\r\n        {\r\n            \"longitude\": -0.127627,\r\n            \"latitude\": 51.503355,\r\n            \"address\": \"Inglaterra 59, La florida, Santiago Chile\",\r\n            \"receiverName\": \"Ignacio Jeria\",\r\n            \"notes\": \"Departamento nº 2214\",\r\n            \"receiverPhone\": \"+56957857558\",\r\n            \"referenceID\": \"reference_1\"\r\n        }\r\n    ],\r\n    \"routes\": [\r\n        {\r\n            \"referenceID\": \"operator-reference-plannedDate\",\r\n            \"operator\": {\r\n                \"referenceID\": \"operatorReference\"\r\n            },\r\n            \"endLocation\": {\r\n                \"nodeReferenceID\": \"12345\",\r\n                \"latitude\": -0.127627,\r\n                \"longitude\": 51.503355\r\n            }\r\n        }\r\n    ]\r\n}",
					"options": {
						"raw": {
							"language": "json"
						}
					}
				},
				"url": {
					"raw": "{{TRANSPORT_APP_HOST}}/plans/optimize",
					"host": [
						"{{TRANSPORT_APP_HOST}}"
					],
					"path": [
						"plans",
						"optimize"
					]
				}
			},
			"response": [
				{
					"name": "ONE ROUTE OPTIMIZATION",
					"originalRequest": {
						"method": "POST",
						"header": [],
						"body": {
							"mode": "raw",
							"raw": "{\r\n    \"referenceID\": \"operator-reference-plannedDate\",\r\n    \"plannedDate\": \"2025-01-03\",\r\n    \"unassignedOrders\": [\r\n        {\r\n            \"referenceID\": \"reference_1\",\r\n            \"latitude\": -12.123456,\r\n            \"longitude\": -77.123456\r\n        }\r\n    ],\r\n    \"routes\": [\r\n        {\r\n            \"referenceID\": \"operator-reference-plannedDate\",\r\n            \"operator\": {\r\n                \"referenceID\": \"operatorReference\"\r\n            }\r\n        }\r\n    ]\r\n}",
							"options": {
								"raw": {
									"language": "json"
								}
							}
						},
						"url": {
							"raw": "{{TRANSPORT_APP_HOST}}/plans/optimize",
							"host": [
								"{{TRANSPORT_APP_HOST}}"
							],
							"path": [
								"plans",
								"optimize"
							]
						}
					},
					"_postman_previewlanguage": "json",
					"header": [
						{
							"key": "Content-Type",
							"value": "application/json",
							"description": "",
							"type": "text"
						}
					],
					"cookie": [],
					"body": "{\n    \"referenceID\": \"reference_8-2025-01-03\",\n    \"plannedDate\": \"2025-01-03\",\n    \"routes\": [\n        {\n            \"referenceID\": \"reference_8-2025-01-03\",\n            \"operator\": {\n                \"referenceID\": \"reference_8\"\n            },\n            \"visits\": [\n                {\n                    \"sequence\": 1,\n                    \"latitude\": 1.0,\n                    \"longitude\": 1.0,\n                    \"orders\": [\n                        {\n                            \"referenceID\": \"reference_1\"\n                        }\n                    ]\n                }\n            ]\n        }\n    ]\n}"
				}
			]
		},
		{
			"name": "UPSERT ORDER",
			"request": {
				"auth": {
					"type": "bearer",
					"bearer": [
						{
							"key": "token",
							"value": "{{FIREBASE_ID_TOKEN}}",
							"type": "string"
						}
					]
				},
				"method": "POST",
				"header": [
					{
						"key": "commerce",
						"value": "COMMERCE_EXAMPLE2AAA",
						"type": "text"
					},
					{
						"key": "consumer",
						"value": "CONSUMER_EXAMPLE",
						"type": "text"
					},
					{
						"key": "organization",
						"value": "150001-CL",
						"type": "text"
					}
				],
				"body": {
					"mode": "raw",
					"raw": "{\r\n    \"referenceID\": \"reference_2\",\r\n    \"collectAvailabilityDate\": {\r\n        \"date\": \"2022-03-10\",\r\n        \"timeRange\": {\r\n            \"endTime\": \"03:41\",\r\n            \"startTime\": \"03:41\"\r\n        }\r\n    },\r\n    \"destination\": {\r\n        \"addressInfo\": {\r\n            \"addressLine1\": \"string24\",\r\n            \"addressLine2\": \"string24\",\r\n            \"addressLine3\": \"string24\",\r\n            \"contact\": {\r\n                \"documents\": [\r\n                    {\r\n                        \"type\": \"string24\",\r\n                        \"value\": \"string24\"\r\n                    }\r\n                ],\r\n                \"email\": \"string24161\",\r\n                \"fullName\": \"string24name\",\r\n                \"nationalID\": \"string24\",\r\n                \"phone\": \"string242\"\r\n            },\r\n            \"locality\": \"string24\",\r\n            \"district\": \"string24\",\r\n            \"latitude\": 100,\r\n            \"longitude\": 100,\r\n            \"province\": \"string24\",\r\n            \"state\": \"string24\",\r\n            \"timeZone\": \"string24\",\r\n            \"zipCode\": \"string24\"\r\n        },\r\n        \"deliveryInstructions\": \"entregar en mi house\",\r\n        \"nodeInfo\": {\r\n            \"referenceId\": \"string244XD\",\r\n            \"name\": \"Ignacio Node 2214\"\r\n        }\r\n    },\r\n    \"items\": [\r\n        {\r\n            \"referenceId\": \"string24\",\r\n            \"description\": \"string24\",\r\n            \"dimensions\": {\r\n                \"Length\": 1,\r\n                \"height\": 1,\r\n                \"unit\": \"string24\",\r\n                \"width\": 1\r\n            },\r\n            \"insurance\": {\r\n                \"currency\": \"CLP\",\r\n                \"unitValue\": 100\r\n            },\r\n            \"logisticCondition\": \"string24\",\r\n            \"quantity\": {\r\n                \"quantityNumber\": 1,\r\n                \"quantityUnit\": \"C/U\"\r\n            },\r\n            \"weight\": {\r\n                \"unit\": \"string24\",\r\n                \"value\": 100\r\n            }\r\n        }\r\n    ],\r\n    \"orderType\": {\r\n        \"description\": \"JOJOJO\",\r\n        \"type\": \"string24\"\r\n    },\r\n    \"origin\": {\r\n        \"addressInfo\": {\r\n            \"addressLine1\": \"string24\",\r\n            \"addressLine2\": \"string24\",\r\n            \"addressLine3\": \"string24\",\r\n            \"contact\": {\r\n                \"documents\": [\r\n                    {\r\n                        \"type\": \"string24\",\r\n                        \"value\": \"string24\"\r\n                    }\r\n                ],\r\n                \"email\": \"string24\",\r\n                \"fullName\": \"string24\",\r\n                \"nationalID\": \"string24\",\r\n                \"phone\": \"string24\"\r\n            },\r\n            \"locality\": \"string24\",\r\n            \"district\": \"string24\",\r\n            \"latitude\": 10,\r\n            \"longitude\": 10,\r\n            \"province\": \"string24\",\r\n            \"state\": \"string24\",\r\n            \"timeZone\": \"string24\",\r\n            \"zipCode\": \"string24\"\r\n        },\r\n        \"nodeInfo\": {\r\n            \"referenceId\": \"string24\",\r\n            \"name\": \"NAXONODE\"\r\n        }\r\n    },\r\n    \"packages\": [\r\n        {\r\n            \"dimensions\": {\r\n                \"Length\": 10,\r\n                \"height\": 10,\r\n                \"unit\": \"string24\",\r\n                \"width\": 10\r\n            },\r\n            \"insurance\": {\r\n                \"currency\": \"string242\",\r\n                \"unitValue\": 10\r\n            },\r\n            \"itemReferences\": [\r\n                {\r\n                    \"quantity\": {\r\n                        \"quantityNumber\": 10,\r\n                        \"quantityUnit\": \"string24\"\r\n                    },\r\n                    \"referenceId\": \"string24\"\r\n                }\r\n            ],\r\n            \"lpn\": \"string24\",\r\n            \"weight\": {\r\n                \"unit\": \"string24\",\r\n                \"value\": 10\r\n            }\r\n        }\r\n    ],\r\n    \"promisedDate\": {\r\n        \"dateRange\": {\r\n            \"endDate\": \"2025-03-10\",\r\n            \"startDate\": \"2025-03-10\"\r\n        },\r\n        \"serviceCategory\": \"string24\",\r\n        \"timeRange\": {\r\n            \"endTime\": \"03:30\",\r\n            \"startTime\": \"03:30\"\r\n        }\r\n    },\r\n    \"references\": [\r\n        {\r\n            \"type\": \"string24\",\r\n            \"value\": \"string24\"\r\n        }\r\n    ],\r\n    \"transportRequirements\": [\r\n        {\r\n            \"type\": \"string24\",\r\n            \"value\": \"string24\"\r\n        }\r\n    ]\r\n}",
					"options": {
						"raw": {
							"language": "json"
						}
					}
				},
				"url": {
					"raw": "{{TRANSPORT_APP_HOST}}/orders",
					"host": [
						"{{TRANSPORT_APP_HOST}}"
					],
					"path": [
						"orders"
					]
				}
			},
			"response": []
		},
		{
			"name": "SEARCH ORDERS BY REFERENCES",
			"request": {
				"auth": {
					"type": "bearer",
					"bearer": [
						{
							"key": "token",
							"value": "{{FIREBASE_ID_TOKEN}}",
							"type": "string"
						}
					]
				},
				"method": "POST",
				"header": [],
				"body": {
					"mode": "raw",
					"raw": "{\r\n    \"referenceIds\": [\r\n        \"reference_1\",\r\n        \"reference_2\",\r\n        \"reference_3\"\r\n    ]\r\n}",
					"options": {
						"raw": {
							"language": "json"
						}
					}
				},
				"url": {
					"raw": "{{TRANSPORT_APP_HOST}}/orders/unique-references-search",
					"host": [
						"{{TRANSPORT_APP_HOST}}"
					],
					"path": [
						"orders",
						"unique-references-search"
					]
				}
			},
			"response": []
		},
		{
			"name": "SEARCH ORDERS BY LPNS",
			"request": {
				"method": "POST",
				"header": [
					{
						"key": "X-Access-Token",
						"value": "{{ACCESS_TOKEN}}",
						"type": "text"
					},
					{
						"key": "organization-key",
						"value": "{{ORGANIZATION_KEY}}",
						"type": "text"
					},
					{
						"key": "country",
						"value": "CL",
						"type": "text"
					}
				],
				"body": {
					"mode": "raw",
					"raw": "{\r\n    \"packageLpns\": [\r\n        \"string24\"\r\n    ]\r\n}",
					"options": {
						"raw": {
							"language": "json"
						}
					}
				},
				"url": {
					"raw": "{{TRANSPORT_APP_HOST}}/orders/lpns-search",
					"host": [
						"{{TRANSPORT_APP_HOST}}"
					],
					"path": [
						"orders",
						"lpns-search"
					]
				}
			},
			"response": []
		},
		{
			"name": "SEARCH ORDERS BY PLAN REFERENCE",
			"request": {
				"auth": {
					"type": "noauth"
				},
				"method": "POST",
				"header": [
					{
						"key": "X-Access-Token",
						"value": "{{ACCESS_TOKEN}}",
						"type": "text"
					},
					{
						"key": "organization-key",
						"value": "{{ORGANIZATION_KEY}}",
						"type": "text"
					},
					{
						"key": "country",
						"value": "CL",
						"type": "text"
					}
				],
				"body": {
					"mode": "raw",
					"raw": "{\r\n    \"operatorReferenceID\":\"1234\",\r\n    \"plannedDate\":\"2025-01-03\"\r\n}",
					"options": {
						"raw": {
							"language": "json"
						}
					}
				},
				"url": {
					"raw": "{{TRANSPORT_APP_HOST}}/orders/daily-plan-search",
					"host": [
						"{{TRANSPORT_APP_HOST}}"
					],
					"path": [
						"orders",
						"daily-plan-search"
					]
				}
			},
			"response": []
		},
		{
			"name": "UPSERT NODE",
			"request": {
				"auth": {
					"type": "noauth"
				},
				"method": "POST",
				"header": [
					{
						"key": "X-Access-Token",
						"value": "{{ACCESS_TOKEN}}",
						"type": "text"
					},
					{
						"key": "organization-key",
						"value": "{{ORGANIZATION_KEY}}",
						"type": "text"
					},
					{
						"key": "country",
						"value": "CL",
						"type": "text"
					},
					{
						"key": "commerce",
						"value": "CORP",
						"type": "text"
					},
					{
						"key": "consumer",
						"value": "CORP",
						"type": "text"
					}
				],
				"body": {
					"mode": "raw",
					"raw": "{\r\n    \"referenceID\": \"referenceIdExample24\",\r\n    \"name\": \"CENTRO DE OPERACION F4\",\r\n    \"type\":\"CENTRO_DE_OPERACION\",\r\n    \"nodeAddress\": {\r\n        \"addressLine1\": \"Inglaterra 59, La florida, Chile\",\r\n        \"addressLine2\": \"\",\r\n        \"addressLine3\": \"\",\r\n        \"locality\": \"La Florida\",\r\n        \"district\": \"Santiago\",\r\n        \"latitude\": -33.5233,\r\n        \"longitude\": -70.5743,\r\n        \"province\": \"Santiago\",\r\n        \"state\": \"Región Metropolitana\",\r\n        \"timeZone\": \"America/Santiago\",\r\n        \"zipCode\": \"8320000\"\r\n    },\r\n    \"operatorContact\": {\r\n        \"email\": \"ignaciovl.j@gmail.com\",\r\n        \"fullName\": \"Ignacio Jeria\",\r\n        \"nationalID\": \"187238123-4\",\r\n        \"phone\": \"+56967283134\"\r\n    }\r\n}",
					"options": {
						"raw": {
							"language": "json"
						}
					}
				},
				"url": {
					"raw": "{{TRANSPORT_APP_HOST}}/nodes",
					"host": [
						"{{TRANSPORT_APP_HOST}}"
					],
					"path": [
						"nodes"
					]
				}
			},
			"response": []
		},
		{
			"name": "SEARCH NODES",
			"request": {
				"auth": {
					"type": "noauth"
				},
				"method": "GET",
				"header": [
					{
						"key": "X-Access-Token",
						"value": "{{ACCESS_TOKEN}}",
						"type": "text"
					},
					{
						"key": "organization-key",
						"value": "{{ORGANIZATION_KEY}}",
						"type": "text"
					},
					{
						"key": "country",
						"value": "CL",
						"type": "text"
					},
					{
						"key": "consumer",
						"value": "CORP",
						"type": "text"
					},
					{
						"key": "commerce",
						"value": "CORP",
						"type": "text"
					}
				],
				"url": {
					"raw": "{{TRANSPORT_APP_HOST}}/nodes?page=0&size=2",
					"host": [
						"{{TRANSPORT_APP_HOST}}"
					],
					"path": [
						"nodes"
					],
					"query": [
						{
							"key": "page",
							"value": "0"
						},
						{
							"key": "size",
							"value": "2"
						}
					]
				}
			},
			"response": []
		},
		{
			"name": "UPSERT VEHICLE",
			"request": {
				"auth": {
					"type": "noauth"
				},
				"method": "POST",
				"header": [
					{
						"key": "X-Access-Token",
						"value": "{{ACCESS_TOKEN}}",
						"type": "text"
					},
					{
						"key": "country",
						"value": "CL",
						"type": "text"
					},
					{
						"key": "organization-key",
						"value": "{{ORGANIZATION_KEY}}",
						"type": "text"
					},
					{
						"key": "commerce",
						"value": "CORP",
						"type": "text"
					},
					{
						"key": "consumer",
						"value": "CORP",
						"type": "text"
					}
				],
				"body": {
					"mode": "raw",
					"raw": "{\r\n    \"referenceID\": \"string\",\r\n    \"carrier\": {\r\n        \"referenceID\":\"my-reference-id-2\",\r\n        \"name\": \"string\",\r\n        \"nationalID\": \"string5\"\r\n    },\r\n    \"category\": \"string\",\r\n    \"certificateDate\": \"string\",\r\n    \"dimensions\": {\r\n        \"height\": 0,\r\n        \"length\": 0,\r\n        \"unitOfMeasure\": \"string\",\r\n        \"width\": 0\r\n    },\r\n    \"insurance\": {\r\n        \"maxInsuranceCoverage\": {\r\n            \"amount\": 0,\r\n            \"currency\": \"string\"\r\n        },\r\n        \"policyExpirationDate\": \"string\",\r\n        \"policyRenewalDate\": \"string\",\r\n        \"policyStartDate\": \"string\"\r\n    },\r\n    \"isActive\": true,\r\n    \"plate\": \"string\",\r\n    \"technicalReview\": {\r\n        \"lastReviewDate\": \"string\",\r\n        \"nextReviewDate\": \"string\",\r\n        \"reviewedBy\": \"string\"\r\n    },\r\n    \"weight\": {\r\n        \"unitOfMeasure\": \"string\",\r\n        \"value\": 0\r\n    }\r\n}",
					"options": {
						"raw": {
							"language": "json"
						}
					}
				},
				"url": {
					"raw": "{{TRANSPORT_APP_HOST}}/vehicles",
					"host": [
						"{{TRANSPORT_APP_HOST}}"
					],
					"path": [
						"vehicles"
					]
				}
			},
			"response": []
		},
		{
			"name": "SEARCH CARRIERS",
			"request": {
				"auth": {
					"type": "noauth"
				},
				"method": "GET",
				"header": [
					{
						"key": "X-Access-Token",
						"value": "{{ACCESS_TOKEN}}",
						"type": "text"
					},
					{
						"key": "organization-key",
						"value": "{{ORGANIZATION_KEY}}",
						"type": "text"
					},
					{
						"key": "country",
						"value": "CL",
						"type": "text"
					}
				],
				"url": {
					"raw": "{{TRANSPORT_APP_HOST}}/carriers?page=0&size=2",
					"host": [
						"{{TRANSPORT_APP_HOST}}"
					],
					"path": [
						"carriers"
					],
					"query": [
						{
							"key": "page",
							"value": "0"
						},
						{
							"key": "size",
							"value": "2"
						}
					]
				}
			},
			"response": []
		},
		{
			"name": "SEARCH VEHICLES BY CARRIER",
			"request": {
				"auth": {
					"type": "noauth"
				},
				"method": "GET",
				"header": [
					{
						"key": "X-Access-Token",
						"value": "{{ACCESS_TOKEN}}",
						"type": "text"
					},
					{
						"key": "organization-key",
						"value": "{{ORGANIZATION_KEY}}",
						"type": "text"
					},
					{
						"key": "country",
						"value": "CL",
						"type": "text"
					}
				],
				"url": {
					"raw": "{{TRANSPORT_APP_HOST}}/carriers/{{referenceID}}/vehicles",
					"host": [
						"{{TRANSPORT_APP_HOST}}"
					],
					"path": [
						"carriers",
						"{{referenceID}}",
						"vehicles"
					]
				}
			},
			"response": []
		},
		{
			"name": "UPSERT OPERATOR",
			"request": {
				"auth": {
					"type": "noauth"
				},
				"method": "POST",
				"header": [
					{
						"key": "X-Access-Token",
						"value": "{{ACCESS_TOKEN}}",
						"type": "text"
					},
					{
						"key": "organization-key",
						"value": "{{ORGANIZATION_KEY}}",
						"type": "text"
					},
					{
						"key": "country",
						"value": "CL",
						"type": "text"
					}
				],
				"body": {
					"mode": "raw",
					"raw": "{\r\n    \"referenceID\": \"reference_8\",\r\n    \"originNodeReferenceID\": \"referenceIdExample24\",\r\n    \"contact\": {\r\n        \"email\": \"ignaciovl8.j@gmail.com\",\r\n        \"fullName\": \"Ignacio Jeria\",\r\n        \"nationalID\": \"187238123-4\",\r\n        \"phone\": \"+56967283134\"\r\n    }\r\n}",
					"options": {
						"raw": {
							"language": "json"
						}
					}
				},
				"url": {
					"raw": "{{TRANSPORT_APP_HOST}}/operators",
					"host": [
						"{{TRANSPORT_APP_HOST}}"
					],
					"path": [
						"operators"
					]
				}
			},
			"response": []
		},
		{
			"name": "SEARCH OPERATOR",
			"request": {
				"auth": {
					"type": "noauth"
				},
				"method": "GET",
				"header": [
					{
						"key": "X-Access-Token",
						"value": "{{ACCESS_TOKEN}}",
						"type": "text"
					},
					{
						"key": "organization-key",
						"value": "{{ORGANIZATION_KEY}}",
						"type": "text"
					},
					{
						"key": "country",
						"value": "CL",
						"type": "text"
					}
				],
				"url": {
					"raw": "{{TRANSPORT_APP_HOST}}/operators?email=ignaciovl8.j@gmail.com",
					"host": [
						"{{TRANSPORT_APP_HOST}}"
					],
					"path": [
						"operators"
					],
					"query": [
						{
							"key": "email",
							"value": "ignaciovl8.j@gmail.com"
						}
					]
				}
			},
			"response": [
				{
					"name": "SEARCH OPERATOR",
					"originalRequest": {
						"method": "GET",
						"header": [
							{
								"key": "Content-Type",
								"value": "application/json",
								"type": "text"
							}
						],
						"url": {
							"raw": "http://localhost:8080/operator?email=ignaciovl.j@gmail.com",
							"protocol": "http",
							"host": [
								"localhost"
							],
							"port": "8080",
							"path": [
								"operator"
							],
							"query": [
								{
									"key": "email",
									"value": "ignaciovl.j@gmail.com"
								}
							]
						}
					},
					"_postman_previewlanguage": "json",
					"header": [
						{
							"key": "Content-Type",
							"value": "application/json",
							"description": "",
							"type": "text"
						}
					],
					"cookie": [],
					"body": "{\r\n    \"referenceID\": \"req-67890\",\r\n    \"contact\": {\r\n        \"email\": \"ignaciovl.j@gmail.com\",\r\n        \"fullName\": \"Ignacio Jeria\",\r\n        \"nationalID\": \"187238123-4\",\r\n        \"phone\": \"+56967283134\"\r\n    },\r\n    \"originNode\": {\r\n        \"referenceID\": \"node-12345\",\r\n        \"name\": \"CENTRO DE OPERACION A\",\r\n        \"type\": \"CENTRO_DE_OPERACION\",\r\n        \"addressInfo\": {\r\n            \"rawAddress\": \"Inglaterra 59, La florida, Chile\",\r\n            \"latitude\": -33.5233,\r\n            \"longitude\": -70.5743\r\n        }\r\n    }\r\n}"
				}
			]
		},
		{
			"name": "CREATE CHECKOUT REJECTION",
			"request": {
				"auth": {
					"type": "noauth"
				},
				"method": "POST",
				"header": [],
				"url": {
					"raw": ""
				}
			},
			"response": []
		},
		{
			"name": "SEARCH CHECKOUT REJECTIONS",
			"request": {
				"method": "GET",
				"header": [],
				"url": {
					"raw": ""
				}
			},
			"response": []
		},
		{
			"name": "CHECKOUT SUBMISSION",
			"request": {
				"auth": {
					"type": "noauth"
				},
				"method": "POST",
				"header": [
					{
						"key": "X-Access-Token",
						"value": "{{ACCESS_TOKEN}}",
						"type": "text"
					},
					{
						"key": "organization-key",
						"value": "{{ORGANIZATION_KEY}}",
						"type": "text"
					},
					{
						"key": "country",
						"value": "CL",
						"type": "text"
					}
				],
				"body": {
					"mode": "raw",
					"raw": "{\r\n    \"plan\": {\r\n        \"referenceID\":\"1234\",\r\n        \"routes\": [\r\n            {\r\n                \"referenceID\": \"reference_1234\",\r\n                \"vehicle\": {\r\n                    \"referenceID\": \"string\",\r\n                    \"plate\": \"string\"\r\n                },\r\n                \"carrier\": {\r\n                    \"referenceID\": \"my-reference-id-2\",\r\n                    \"nationalID\": \"string5\"\r\n                },\r\n                \"operator\": {\r\n                    \"referenceID\": \"12345\"\r\n                },\r\n                \"visits\": [\r\n                    {\r\n                        \"referenceID\": \"123456\",\r\n                        \"location\": {\r\n                            \"latitude\": -12.123456,\r\n                            \"longitude\": -77.123456\r\n                        },\r\n                        \"orders\": [\r\n                            {\r\n                                \"referenceID\": \"order_ref_value\",\r\n                                \"reportedAt\": \"2024-02-02T15:30:00Z\",\r\n                                \"status\": \"finished/pending\",\r\n                                \"businessIdentifiers\": {\r\n                                    \"commerce\": \"COMMERCE_EXAMPLE2AAA\",\r\n                                    \"consumer\": \"CONSUMER_EXAMPLE\"\r\n                                },\r\n                                \"deliveredAt\": \"2024-02-02T15:30:00Z\",\r\n                                \"recipient\": {\r\n                                    \"fullName\": \"\",\r\n                                    \"nationalID\": \"\"\r\n                                },\r\n                                \"evidencePhotos\": [\r\n                                    {\r\n                                        \"url\": \"https://example.com/photo1.jpg\",\r\n                                        \"type\": \"DELIVERY_PROOF\",\r\n                                        \"takenAt\": \"2024-02-02T15:30:00Z\"\r\n                                    }\r\n                                ],\r\n                                \"failure\": {\r\n                                    \"referenceID\": \"1234\",\r\n                                    \"reason\": \"NO_RESIDENTS\",\r\n                                    \"detail\": \"No se encontraron moradores\"\r\n                                }\r\n                            }\r\n                        ]\r\n                    }\r\n                ]\r\n            }\r\n        ]\r\n    }\r\n}",
					"options": {
						"raw": {
							"language": "json"
						}
					}
				},
				"url": {
					"raw": "{{TRANSPORT_APP_HOST}}/checkouts",
					"host": [
						"{{TRANSPORT_APP_HOST}}"
					],
					"path": [
						"checkouts"
					]
				}
			},
			"response": []
		},
		{
			"name": "DIRECTIONS AUTOCOMPLETE",
			"request": {
				"method": "GET",
				"header": [],
				"url": {
					"raw": "https://einar-main-f0820bc.d2.zuplo.dev/autocomplete?q=inglaterra%2059,%20la%20florida,%20santiago,%20chile&limit=5&dedupe=1&accept-language=es",
					"protocol": "https",
					"host": [
						"einar-main-f0820bc",
						"d2",
						"zuplo",
						"dev"
					],
					"path": [
						"autocomplete"
					],
					"query": [
						{
							"key": "q",
							"value": "inglaterra%2059,%20la%20florida,%20santiago,%20chile"
						},
						{
							"key": "limit",
							"value": "5"
						},
						{
							"key": "dedupe",
							"value": "1"
						},
						{
							"key": "accept-language",
							"value": "es"
						}
					]
				}
			},
			"response": []
		},
		{
			"name": "DIRECTIONS NORMALIZATION",
			"request": {
				"auth": {
					"type": "noauth"
				},
				"method": "POST",
				"header": [],
				"body": {
					"mode": "raw",
					"raw": "{\r\n    \"providerInput\": {\r\n        \"displayName\": \"Inglaterra, Bellavista de La Florida, La Florida, Provincia de Santiago, Santiago Metropolitan Region, 8260183, Chile\"\r\n    },\r\n    \"userInput\": {\r\n        \"addressLine1\": \"INGLATERRA 59\",\r\n        \"addressLine2\": \"piso 1\"\r\n    }\r\n}",
					"options": {
						"raw": {
							"language": "json"
						}
					}
				},
				"url": {
					"raw": "{{TRANSPORT_APP_HOST}}/normalization",
					"host": [
						"{{TRANSPORT_APP_HOST}}"
					],
					"path": [
						"normalization"
					]
				}
			},
			"response": []
		},
		{
			"name": "GEOCODING",
			"request": {
				"auth": {
					"type": "noauth"
				},
				"method": "GET",
				"header": [],
				"url": {
					"raw": "https://einar-main-f0820bc.d2.zuplo.dev/geocode?q=Inglaterra%2C%20Bellavista%20de%20La%20Florida%2C%20La%20Florida%2C%20Provincia%20de%20Santiago%2C%20Santiago%20Metropolitan%20Region%2C%208260183%2C%20Chile&format=json&",
					"protocol": "https",
					"host": [
						"einar-main-f0820bc",
						"d2",
						"zuplo",
						"dev"
					],
					"path": [
						"geocode"
					],
					"query": [
						{
							"key": "q",
							"value": "Inglaterra%2C%20Bellavista%20de%20La%20Florida%2C%20La%20Florida%2C%20Provincia%20de%20Santiago%2C%20Santiago%20Metropolitan%20Region%2C%208260183%2C%20Chile"
						},
						{
							"key": "format",
							"value": "json"
						},
						{
							"key": "",
							"value": null
						}
					]
				}
			},
			"response": []
		},
		{
			"name": "https://api.deepseek.com/chat/completions",
			"request": {
				"method": "POST",
				"header": [
					{
						"key": "Content-Type",
						"value": "application/json"
					},
					{
						"key": "Authorization",
						"value": "Bearer sk-66c256548b2b4bc39f1e771eb4a398bc"
					}
				],
				"body": {
					"mode": "raw",
					"raw": "{\r\n  \"model\": \"deepseek-chat\",\r\n  \"messages\": [\r\n    {\r\n      \"role\": \"system\",\r\n      \"content\": \"You are an assistant that normalizes addresses in Chile following a structured format. Always return a JSON with the following fields: AddressLine1, AddressLine2, Comune, Region, and Country. Use 'AddressLine2' only for apartment, house number, block, or specific location details. If no additional details exist, return an empty string for AddressLine2. Never duplicate the Comune in AddressLine2.\"\r\n    },\r\n    {\r\n      \"role\": \"user\",\r\n      \"content\": \"Normalize the following address and return a JSON:\\n\\nUser Input: inglaterra 59, la florida chile\\nLocationIQ Output: Inglaterra, Bellavista de La Florida, La Florida, Provincia de Santiago, Santiago Metropolitan Region, 8260183, Chile\\nCoordinates: -33.5150979, -70.6083496\"\r\n    }\r\n  ],\r\n  \"stream\": false\r\n}\r\n",
					"options": {
						"raw": {
							"language": "json"
						}
					}
				},
				"url": {
					"raw": "https://api.deepseek.com/chat/completions",
					"protocol": "https",
					"host": [
						"api",
						"deepseek",
						"com"
					],
					"path": [
						"chat",
						"completions"
					]
				},
				"description": "Generated from cURL: curl https://api.deepseek.com/chat/completions \\\r\n  -H \"Content-Type: application/json\" \\\r\n  -H \"Authorization: Bearer <DeepSeek API Key>\" \\\r\n  -d '{\r\n        \"model\": \"deepseek-chat\",\r\n        \"messages\": [\r\n          {\"role\": \"system\", \"content\": \"You are a helpful assistant.\"},\r\n          {\"role\": \"user\", \"content\": \"Hello!\"}\r\n        ],\r\n        \"stream\": false\r\n      }'"
			},
			"response": []
		},
		{
			"name": "REPORT",
			"request": {
				"method": "GET",
				"header": []
			},
			"response": []
		}
	],
	"event": [
		{
			"listen": "prerequest",
			"script": {
				"type": "text/javascript",
				"exec": [
					""
				]
			}
		},
		{
			"listen": "test",
			"script": {
				"type": "text/javascript",
				"exec": [
					""
				]
			}
		}
	],
	"variable": [
		{
			"key": "referenceID",
			"value": "",
			"type": "default"
		},
		{
			"key": "planID",
			"value": "",
			"type": "default"
		},
		{
			"key": "ZUPLO_HOST",
			"value": "",
			"type": "default"
		},
		{
			"key": "TRANSPORT_APP_HOST",
			"value": "localhost:8080",
			"type": "default"
		},
		{
			"key": "ZUPLO_API_KEY",
			"value": "Bearer zpka_e418578185d84230b0e808761c6ba380_29db53d5",
			"type": "default"
		},
		{
			"key": "API_KEY",
			"value": "Bearer zpka_e418578185d84230b0e808761c6ba380_29db53d5",
			"type": "default"
		},
		{
			"key": "ACCESS_TOKEN",
			"value": "zpka_436d2dc5fe614d24bbbfc61013e28484_38827f47",
			"type": "default"
		},
		{
			"key": "ORGANIZATION_KEY",
			"value": "a25d627d-cc07-4efe-a071-dc76aff4b77b-0ec942d5-c66b-4843-8712-62fd30fee9de",
			"type": "default"
		},
		{
			"key": "FIREBASE_ID_TOKEN",
			"value": "eyJhbGciOiJSUzI1NiIsImtpZCI6ImJjNDAxN2U3MGE4MWM5NTMxY2YxYjY4MjY4M2Q5OThlNGY1NTg5MTkiLCJ0eXAiOiJKV1QifQ.eyJwcmltYXJ5X29yZyI6IjYwMDAxLUNMIiwiaXNzIjoiaHR0cHM6Ly9zZWN1cmV0b2tlbi5nb29nbGUuY29tL2VpbmFyLTQwNDYyMyIsImF1ZCI6ImVpbmFyLTQwNDYyMyIsImF1dGhfdGltZSI6MTc0MTc0NjcyOSwidXNlcl9pZCI6Ik1xY001Q2NGTmlOblNsVzl6WnJVWEQ4RWo5UzIiLCJzdWIiOiJNcWNNNUNjRk5pTm5TbFc5elpyVVhEOEVqOVMyIiwiaWF0IjoxNzQxNzQ2NzI5LCJleHAiOjE3NDE3NTAzMjksImVtYWlsIjoiaWduYWNpb3ZsLmpAZ21haWwuY29tIiwiZW1haWxfdmVyaWZpZWQiOmZhbHNlLCJmaXJlYmFzZSI6eyJpZGVudGl0aWVzIjp7ImVtYWlsIjpbImlnbmFjaW92bC5qQGdtYWlsLmNvbSJdfSwic2lnbl9pbl9wcm92aWRlciI6InBhc3N3b3JkIn19.vKbB3ERxTQajjO0szpPC_Rm-RXlxE9RDPr0cknZz36zLmMM6_aaogaezcJMiAdF5hRBEVu-hDhTuXh3P16erwj8OMNfHiK8_8DKt9I3DRMAWEYjp3D3-9glYi6yfa1D32z1lQOt_nn_nSEd2n7gLTt3h7Gv9QfEzvM6OIbyZk1kCaGhilT5QdoV6C97fw3ihU9jMQm2mdKfn9_i4QmCtlcBxM38b-xlAZQP6cTDYNptyai2XsAALTxn6CSL3n-NhfSCtEgAYUTCStvNGtPb7uvr-cvM3KzTN_zKE6P05YtsBg9fb5qy1M1VGjNPahJI1Jlr57MU2ooSl4vRbN3edWQ",
			"type": "default"
		}
	]
}